Metadata-Version: 2.0
Name: FC-CloudTrails-SDK
Version: 1.0.4
Summary: SDK for CloudTrails DevOps management
Home-page: https://bitbucket.org/elasbit/fc-cloudtrails-sdk-py
Author: Yaisel Hurtado, Raydel Miranda, Yordano Gonzalez
Author-email: hurta2yaisel@gmail.com, raydel.miranda.gomez@gmail.com, yorda891216@gmail.com
License: UNKNOWN
Platform: UNKNOWN
Classifier: Programming Language :: Python :: 2
Classifier: Operating System :: OS Independent
